findacat/__init__.py
findacat/client.py
findacat/models/__init__.py
findacat/models/cat_options.py
findacat-1.0.0.dist-info/licenses/LICENCE.md
findacat-1.0.0.dist-info/METADATA
findacat-1.0.0.dist-info/WHEEL
findacat-1.0.0.dist-info/top_level.txt
findacat-1.0.0.dist-info/RECORD
