Metadata-Version: 2.4
Name: findacat
Version: 1.0.0
Summary: A lightweight Python wrapper for the finda.cat API.
Home-page: https://github.com/raz461/findacat-py
Author: Never
License: MIT
Project-URL: Homepage, https://github.com/raz461/findacat
Project-URL: Repository, https://github.com/raz461/findacat-py
Project-URL: BugTracker, https://github.com/raz461/findacat-py/issues
Requires-Python: >=3.10
License-File: LICENCE.md
Requires-Dist: requests
Dynamic: home-page
Dynamic: license-file
Dynamic: requires-python
